dccs/__init__.py
dccs-0.0.1.dist-info/LICENSE
dccs-0.0.1.dist-info/METADATA
dccs-0.0.1.dist-info/WHEEL
dccs-0.0.1.dist-info/top_level.txt
dccs-0.0.1.dist-info/RECORD
