Metadata-Version: 2.1
Name: dccs
Version: 0.0.1
Summary: Connect to any DCC tool from anywhere.
Home-page: https://github.com/coreprocess/dccl/dccs
Author: Niklas Salmoukas
Author-email: niklas@salmoukas.com
License: LGPLv3
Platform: UNKNOWN
Classifier: Programming Language :: Python :: 3
Classifier: License :: OSI Approved :: GNU Lesser General Public License v3 (LGPLv3)
Classifier: Operating System :: OS Independent
Requires-Python: >=3.6
